utils/__init__.py
utils/data_input.py
utils/generalfunc.py
utils/noise_sidefunc.py
utils/phone_error_rate.py
utils/standardizer.py
utils/timit_load.py
asrassessment-0.0.14.dist-info/LICENSE.txt
asrassessment-0.0.14.dist-info/METADATA
asrassessment-0.0.14.dist-info/WHEEL
asrassessment-0.0.14.dist-info/top_level.txt
asrassessment-0.0.14.dist-info/RECORD
