Metadata-Version: 2.1
Name: asrassessment
Version: 0.0.14
Summary: Provides Phoneme Error Rate & Visualisation Assessment
Home-page: 
Author: Jonathan Lim
Author-email: Jonathanlimws@gmail.com
License: MIT
Keywords: ASR
Classifier: Development Status :: 5 - Production/Stable
Classifier: Intended Audience :: Science/Research
Classifier: Operating System :: MacOS
Classifier: License :: OSI Approved :: MIT License
Classifier: Programming Language :: Python :: 3
License-File: LICENSE.txt
Requires-Dist: glob2 (==0.7)
Requires-Dist: tqdm (==4.64.0)
Requires-Dist: librosa (==0.9.2)
Requires-Dist: scipy (==1.9.0)
Requires-Dist: numpy (==1.23.1)
Requires-Dist: pandas (==1.4.3)
Requires-Dist: sklearn (==0.0)
Requires-Dist: pydub (==0.25.1)
Requires-Dist: soundfile (==0.10.3.post1)
